jspec/__init__.py
jspec/check.py
jspec/entity.py
jspec/matcher.py
jspec/parse.py
jspec/scanner.py
jspec-2.1.4.dist-info/LICENSE
jspec-2.1.4.dist-info/METADATA
jspec-2.1.4.dist-info/WHEEL
jspec-2.1.4.dist-info/top_level.txt
jspec-2.1.4.dist-info/RECORD
