Metadata-Version: 2.1
Name: jspec
Version: 2.1.4
Summary: JSPEC is a powerful yet simple and lightweight JSON validation module
Home-page: https://github.com/chrismalcolm/jspec
Author: Christopher Malcolm
Author-email: chris.c.malcolm.96@gmail.com
License: MIT
Platform: UNKNOWN
Classifier: Programming Language :: Python :: 3.6
Classifier: Programming Language :: Python :: 3.7
Classifier: Programming Language :: Python :: 3.8
Classifier: Programming Language :: Python :: 3.9
Classifier: Programming Language :: Python :: 3.10
License-File: LICENSE
